molecule_ec2/__init__.py
molecule_ec2/driver.py
molecule_ec2/cookiecutter/cookiecutter.json
molecule_ec2/cookiecutter/{{cookiecutter.molecule_directory}}/{{cookiecutter.scenario_name}}/INSTALL.rst
molecule_ec2/cookiecutter/{{cookiecutter.molecule_directory}}/{{cookiecutter.scenario_name}}/converge.yml
molecule_ec2/cookiecutter/{{cookiecutter.molecule_directory}}/{{cookiecutter.scenario_name}}/create.yml
molecule_ec2/cookiecutter/{{cookiecutter.molecule_directory}}/{{cookiecutter.scenario_name}}/destroy.yml
molecule_ec2/cookiecutter/{{cookiecutter.molecule_directory}}/{{cookiecutter.scenario_name}}/prepare.yml
molecule_ec2/test/__init__.py
molecule_ec2/test/test_driver.py
molecule_ec2/test/functional/.ansible-lint
molecule_ec2/test/functional/__init__.py
molecule_ec2/test/functional/conftest.py
molecule_ec2/test/functional/test_ec2.py
molecule_ec2/test/scenarios/driver/ec2/molecule/default/converge.yml
molecule_ec2/test/scenarios/driver/ec2/molecule/default/molecule.yml
molecule_ec2/test/scenarios/driver/ec2/molecule/default/prepare.yml
molecule_ec2/test/scenarios/driver/ec2/molecule/default/tests/test_default.py
molecule_ec2/test/scenarios/driver/ec2/molecule/multi-node/converge.yml
molecule_ec2/test/scenarios/driver/ec2/molecule/multi-node/molecule.yml
molecule_ec2/test/scenarios/driver/ec2/molecule/multi-node/prepare.yml
molecule_ec2/test/scenarios/driver/ec2/molecule/multi-node/tests/__init__.py
molecule_ec2/test/scenarios/driver/ec2/molecule/multi-node/tests/test_default.py
molecule_ec2-0.4.dist-info/LICENSE
molecule_ec2-0.4.dist-info/METADATA
molecule_ec2-0.4.dist-info/WHEEL
molecule_ec2-0.4.dist-info/entry_points.txt
molecule_ec2-0.4.dist-info/top_level.txt
molecule_ec2-0.4.dist-info/RECORD
