Metadata-Version: 2.1
Name: molecule-ec2
Version: 0.4
Summary: EC2 Molecule Plugin :: run molecule tests using AWS EC2
Home-page: https://github.com/ansible-community/molecule-ec2
Author: Sorin Sbarnea
Author-email: sorin.sbarnea@gmail.com
Maintainer: Sorin Sbarnea
Maintainer-email: sorin.sbarnea@gmail.com
License: MIT
Project-URL: Bug Tracker, https://github.com/ansible-community/molecule-ec2/issues
Project-URL: Release Management, https://github.com/ansible-community/molecule-ec2/releases
Project-URL: CI: Zuul, https://dashboard.zuul.ansible.com/t/ansible/builds?project=ansible-community/molecule-ec2
Project-URL: Source Code, https://github.com/ansible-community/molecule-ec2
Keywords: ansible,roles,testing,molecule,plugin,ec2,aws,boto
Platform: UNKNOWN
Classifier: Development Status :: 5 - Production/Stable
Classifier: Environment :: Console
Classifier: Framework :: Pytest
Classifier: Intended Audience :: Developers
Classifier: Intended Audience :: Information Technology
Classifier: Intended Audience :: System Administrators
Classifier: License :: OSI Approved :: MIT License
Classifier: Natural Language :: English
Classifier: Operating System :: OS Independent
Classifier: Programming Language :: Python :: 3
Classifier: Programming Language :: Python :: 3.6
Classifier: Programming Language :: Python :: 3.7
Classifier: Programming Language :: Python :: 3.8
Classifier: Programming Language :: Python :: 3.9
Classifier: Topic :: System :: Systems Administration
Classifier: Topic :: Utilities
Requires-Python: >=3.6
License-File: LICENSE
Requires-Dist: molecule (>=3.2)
Requires-Dist: pyyaml (>=5.1)
Requires-Dist: boto3 ; platform_system == "Windows"
Provides-Extra: test
Requires-Dist: molecule[test] ; extra == 'test'
